varnishlog_to_elasticsearch/__init__.py
varnishlog_to_elasticsearch/cli.py
varnishlog_to_elasticsearch/parser.py
varnishlog_to_elasticsearch/vsl.py
varnishlog_to_elasticsearch-0.2.0.dist-info/METADATA
varnishlog_to_elasticsearch-0.2.0.dist-info/WHEEL
varnishlog_to_elasticsearch-0.2.0.dist-info/entry_points.txt
varnishlog_to_elasticsearch-0.2.0.dist-info/top_level.txt
varnishlog_to_elasticsearch-0.2.0.dist-info/RECORD
