Metadata-Version: 2.4
Name: varnishlog-to-elasticsearch
Version: 0.2.0
Summary: A tool to parse Varnish HTTP logs and send them to Elasticsearch
Home-page: https://github.com/NIXRUK/varnishlog-to-elasticsearch
Author: Will Riches
Author-email: will@nixr.com
Classifier: Development Status :: 4 - Beta
Classifier: Intended Audience :: System Administrators
Classifier: License :: OSI Approved :: MIT License
Classifier: Operating System :: OS Independent
Classifier: Programming Language :: Python :: 3
Classifier: Programming Language :: Python :: 3.8
Classifier: Programming Language :: Python :: 3.9
Classifier: Programming Language :: Python :: 3.10
Classifier: Programming Language :: Python :: 3.11
Requires-Python: >=3.8
Requires-Dist: requests>=2.31.0
Requires-Dist: urllib3>=2.0.0
Dynamic: author
Dynamic: author-email
Dynamic: classifier
Dynamic: description
Dynamic: description-content-type
Dynamic: home-page
Dynamic: requires-dist
Dynamic: requires-python
Dynamic: summary
